ua_ilab_tools/__init__.py
ua_ilab_tools/api_types.py
ua_ilab_tools/extract_custom_forms.py
ua_ilab_tools/ilab_api.py
ua_ilab_tools/tests/extract_custom_form_info_samples_con_type_tube.xml
ua_ilab_tools/tests/extract_custom_form_info_samples_not_ascii_characters.xml
ua_ilab_tools/tests/extract_from_grid_con_type_eight_strip.xml
ua_ilab_tools/tests/extract_from_grid_con_type_eight_strip_too_many_tubes.xml
ua_ilab_tools/tests/extract_from_grid_container_name_in_form.xml
ua_ilab_tools/tests/extract_from_grid_container_name_in_grid.xml
ua_ilab_tools/tests/extract_from_grid_lvs_primers.xml
ua_ilab_tools/tests/extract_from_grid_tgm_data.xml
ua_ilab_tools/tests/test_ilab_tools.py
ua_ilab_tools/ua_ilab_tools.py
ua_ilab_tools-2.1.4.dist-info/LICENSE
ua_ilab_tools-2.1.4.dist-info/METADATA
ua_ilab_tools-2.1.4.dist-info/WHEEL
ua_ilab_tools-2.1.4.dist-info/RECORD
